[{"model": "auth.permission", "pk": 1, "fields": {"name": "Can add log entry", "content_type": 1, "codename": "add_logentry"}}, {"model": "auth.permission", "pk": 2, "fields": {"name": "Can change log entry", "content_type": 1, "codename": "change_logentry"}}, {"model": "auth.permission", "pk": 3, "fields": {"name": "Can delete log entry", "content_type": 1, "codename": "delete_logentry"}}, {"model": "auth.permission", "pk": 4, "fields": {"name": "Can view log entry", "content_type": 1, "codename": "view_logentry"}}, {"model": "auth.permission", "pk": 5, "fields": {"name": "Can add permission", "content_type": 2, "codename": "add_permission"}}, {"model": "auth.permission", "pk": 6, "fields": {"name": "Can change permission", "content_type": 2, "codename": "change_permission"}}, {"model": "auth.permission", "pk": 7, "fields": {"name": "Can delete permission", "content_type": 2, "codename": "delete_permission"}}, {"model": "auth.permission", "pk": 8, "fields": {"name": "Can view permission", "content_type": 2, "codename": "view_permission"}}, {"model": "auth.permission", "pk": 9, "fields": {"name": "Can add group", "content_type": 3, "codename": "add_group"}}, {"model": "auth.permission", "pk": 10, "fields": {"name": "Can change group", "content_type": 3, "codename": "change_group"}}, {"model": "auth.permission", "pk": 11, "fields": {"name": "Can delete group", "content_type": 3, "codename": "delete_group"}}, {"model": "auth.permission", "pk": 12, "fields": {"name": "Can view group", "content_type": 3, "codename": "view_group"}}, {"model": "auth.permission", "pk": 13, "fields": {"name": "Can add user", "content_type": 4, "codename": "add_user"}}, {"model": "auth.permission", "pk": 14, "fields": {"name": "Can change user", "content_type": 4, "codename": "change_user"}}, {"model": "auth.permission", "pk": 15, "fields": {"name": "Can delete user", "content_type": 4, "codename": "delete_user"}}, {"model": "auth.permission", "pk": 16, "fields": {"name": "Can view user", "content_type": 4, "codename": "view_user"}}, {"model": "auth.permission", "pk": 17, "fields": {"name": "Can add content type", "content_type": 5, "codename": "add_contenttype"}}, {"model": "auth.permission", "pk": 18, "fields": {"name": "Can change content type", "content_type": 5, "codename": "change_contenttype"}}, {"model": "auth.permission", "pk": 19, "fields": {"name": "Can delete content type", "content_type": 5, "codename": "delete_contenttype"}}, {"model": "auth.permission", "pk": 20, "fields": {"name": "Can view content type", "content_type": 5, "codename": "view_contenttype"}}, {"model": "auth.permission", "pk": 21, "fields": {"name": "Can add session", "content_type": 6, "codename": "add_session"}}, {"model": "auth.permission", "pk": 22, "fields": {"name": "Can change session", "content_type": 6, "codename": "change_session"}}, {"model": "auth.permission", "pk": 23, "fields": {"name": "Can delete session", "content_type": 6, "codename": "delete_session"}}, {"model": "auth.permission", "pk": 24, "fields": {"name": "Can view session", "content_type": 6, "codename": "view_session"}}, {"model": "auth.permission", "pk": 25, "fields": {"name": "Can add Заемщик", "content_type": 7, "codename": "add_borrower"}}, {"model": "auth.permission", "pk": 26, "fields": {"name": "Can change Заемщик", "content_type": 7, "codename": "change_borrower"}}, {"model": "auth.permission", "pk": 27, "fields": {"name": "Can delete Заемщик", "content_type": 7, "codename": "delete_borrower"}}, {"model": "auth.permission", "pk": 28, "fields": {"name": "Can view Заемщик", "content_type": 7, "codename": "view_borrower"}}, {"model": "auth.permission", "pk": 29, "fields": {"name": "Can add Займодатель", "content_type": 8, "codename": "add_lender"}}, {"model": "auth.permission", "pk": 30, "fields": {"name": "Can change Займодатель", "content_type": 8, "codename": "change_lender"}}, {"model": "auth.permission", "pk": 31, "fields": {"name": "Can delete Займодатель", "content_type": 8, "codename": "delete_lender"}}, {"model": "auth.permission", "pk": 32, "fields": {"name": "Can view Займодатель", "content_type": 8, "codename": "view_lender"}}, {"model": "auth.permission", "pk": 33, "fields": {"name": "Can add Платеж", "content_type": 9, "codename": "add_payment"}}, {"model": "auth.permission", "pk": 34, "fields": {"name": "Can change Платеж", "content_type": 9, "codename": "change_payment"}}, {"model": "auth.permission", "pk": 35, "fields": {"name": "Can delete Платеж", "content_type": 9, "codename": "delete_payment"}}, {"model": "auth.permission", "pk": 36, "fields": {"name": "Can view Платеж", "content_type": 9, "codename": "view_payment"}}, {"model": "auth.permission", "pk": 37, "fields": {"name": "Can add Счет", "content_type": 10, "codename": "add_score"}}, {"model": "auth.permission", "pk": 38, "fields": {"name": "Can change Счет", "content_type": 10, "codename": "change_score"}}, {"model": "auth.permission", "pk": 39, "fields": {"name": "Can delete Счет", "content_type": 10, "codename": "delete_score"}}, {"model": "auth.permission", "pk": 40, "fields": {"name": "Can view Счет", "content_type": 10, "codename": "view_score"}}, {"model": "auth.user", "pk": 1, "fields": {"password": "pbkdf2_sha256$216000$h4mI6KV9jQh5$jAoACZC3bANwol4jS2Jb4mUVPKtKfPB6CoapoAHwtOk=", "last_login": "2021-03-06T11:25:05.525Z", "is_superuser": true, "username": "admin", "first_name": "", "last_name": "", "email": "", "is_staff": true, "is_active": true, "date_joined": "2021-02-25T11:30:17.384Z", "groups": [], "user_permissions": []}}, {"model": "contenttypes.contenttype", "pk": 1, "fields": {"app_label": "admin", "model": "logentry"}}, {"model": "contenttypes.contenttype", "pk": 2, "fields": {"app_label": "auth", "model": "permission"}}, {"model": "contenttypes.contenttype", "pk": 3, "fields": {"app_label": "auth", "model": "group"}}, {"model": "contenttypes.contenttype", "pk": 4, "fields": {"app_label": "auth", "model": "user"}}, {"model": "contenttypes.contenttype", "pk": 5, "fields": {"app_label": "contenttypes", "model": "contenttype"}}, {"model": "contenttypes.contenttype", "pk": 6, "fields": {"app_label": "sessions", "model": "session"}}, {"model": "contenttypes.contenttype", "pk": 7, "fields": {"app_label": "server", "model": "borrower"}}, {"model": "contenttypes.contenttype", "pk": 8, "fields": {"app_label": "server", "model": "lender"}}, {"model": "contenttypes.contenttype", "pk": 9, "fields": {"app_label": "server", "model": "payment"}}, {"model": "contenttypes.contenttype", "pk": 10, "fields": {"app_label": "server", "model": "score"}}, {"model": "sessions.session", "pk": "5wjb30hp93abu0n1o7clp91cqakdvx3q", "fields": {"session_data": ".eJxVjEEOwiAQRe_C2pAyDBRcuu8ZmgEGWzWQlHZlvLsh6UK3_73332KmY1_mo_E2r0lchRKX3y1QfHLpID2o3KuMtezbGmRX5EmbnGri1-10_w4Wakuvh1ERmxANordgXdR5HLz2drAOMwXMViMAGmfAeXaOySIbHk0GBSA-X705Np8:1lFEqr:xpm93v6xhpyeqcJml6jJHg0ULaQOl6JH3B7YgqLXWzk", "expire_date": "2021-03-11T11:30:37.713Z"}}, {"model": "sessions.session", "pk": "npm22hz9i6nj0rbpacxitf00kp8hd2d1", "fields": {"session_data": ".eJxVjEEOwiAQRe_C2pAyDBRcuu8ZmgEGWzWQlHZlvLsh6UK3_73332KmY1_mo_E2r0lchRKX3y1QfHLpID2o3KuMtezbGmRX5EmbnGri1-10_w4Wakuvh1ERmxANordgXdR5HLz2drAOMwXMViMAGmfAeXaOySIbHk0GBSA-X705Np8:1lIV3R:MQyMuiSPatF_aSDzAARJIjjagVZGcABqkVzg-Da7e20", "expire_date": "2021-03-20T11:25:05.543Z"}}, {"model": "server.score", "pk": 9, "fields": {"total": 7000000, "leftover": 7000000, "monthly_payment": 0, "total_payment": 0, "date_score": "2021-03-06T06:44:15.501Z", "payment_status": "подтвержден"}}, {"model": "server.score", "pk": 10, "fields": {"total": 7000000, "leftover": 6934434, "monthly_payment": 65566, "total_payment": 65566, "date_score": "2021-03-06T08:49:47.057Z", "payment_status": "подтверждено"}}, {"model": "server.score", "pk": 11, "fields": {"total": 7000000, "leftover": 6884434, "monthly_payment": 50000, "total_payment": 115566, "date_score": "2021-03-06T09:03:27.955Z", "payment_status": "подтверждено"}}, {"model": "server.score", "pk": 12, "fields": {"total": 7000000, "leftover": 6784434, "monthly_payment": 100000, "total_payment": 215566, "date_score": "2021-03-06T10:10:08.720Z", "payment_status": "подтверждено"}}, {"model": "server.score", "pk": 13, "fields": {"total": 7000000, "leftover": 6734434, "monthly_payment": 50000, "total_payment": 265566, "date_score": "2021-03-06T10:11:52.567Z", "payment_status": "подтверждено"}}, {"model": "server.payment", "pk": 8, "fields": {"payment_date": "2021-03-06T08:49:47.030Z", "monthly_payment": 65566}}, {"model": "server.payment", "pk": 9, "fields": {"payment_date": "2021-03-06T09:03:27.927Z", "monthly_payment": 50000}}, {"model": "server.payment", "pk": 10, "fields": {"payment_date": "2021-03-06T10:10:08.692Z", "monthly_payment": 100000}}, {"model": "server.payment", "pk": 11, "fields": {"payment_date": "2021-03-06T10:11:52.540Z", "monthly_payment": 50000}}, {"model": "server.lender", "pk": 2, "fields": {"lender_id": 1666640130}}, {"model": "server.borrower", "pk": 2, "fields": {"borrower_id": 936645515}}]